setup.py
saboohi_dsnd/Binomialdistribution.py
saboohi_dsnd/Gaussiandistribution.py
saboohi_dsnd/Generaldistribution.py
saboohi_dsnd/__init__.py
saboohi_dsnd.egg-info/PKG-INFO
saboohi_dsnd.egg-info/SOURCES.txt
saboohi_dsnd.egg-info/dependency_links.txt
saboohi_dsnd.egg-info/not-zip-safe
saboohi_dsnd.egg-info/top_level.txt