Metadata-Version: 1.0
Name: saboohi-dsnd
Version: 0.1
Summary: Gaussian and Binomial distributions
Home-page: UNKNOWN
Author: Saboohi Dhawan
Author-email: saboohi.dhawan@gmail.com
License: UNKNOWN
Platform: UNKNOWN
